timeleft/__init__.py
timeleft/timeleft.py
timeleft-0.2.dist-info/DESCRIPTION.rst
timeleft-0.2.dist-info/METADATA
timeleft-0.2.dist-info/RECORD
timeleft-0.2.dist-info/WHEEL
timeleft-0.2.dist-info/entry_points.txt
timeleft-0.2.dist-info/metadata.json
timeleft-0.2.dist-info/top_level.txt
