Metadata-Version: 2.0
Name: timeleft
Version: 0.2
Summary: A simple command line utility for displaying the amount of time left in a download.
Home-page: https://github.com/srwareham/timeleft
Author: Sean Wareham
Author-email: UNKNOWN
License: GPL 3.0
Platform: UNKNOWN
Classifier: Development Status :: 3 - Alpha
Classifier: Environment :: ConsoleIntended Audience :: End Users/Desktop
Classifier: Natural Language :: English
Classifier: License :: OSI Approved :: GNU General Public License v3 (GPLv3)
Classifier: Operating System :: OS Independent
Classifier: Programming Language :: Python
Classifier: Programming Language :: Python :: 2.6
Classifier: Programming Language :: Python :: 2.7
Classifier: Programming Language :: Python :: 3
Classifier: Programming Language :: Python :: 3.3
Classifier: Programming Language :: Python :: 3.4
Classifier: Programming Language :: Python :: 3.5
Classifier: Programming Language :: Python :: Implementation :: CPython
Classifier: Programming Language :: Python :: Implementation :: PyPy
Classifier: Topic :: Internet
Classifier: Topic :: Terminals
Classifier: Topic :: Utilities
